pexelsbot/__init__.py
pexelsbot/pexels.py
pexelsbot-0.0.1.dist-info/METADATA
pexelsbot-0.0.1.dist-info/WHEEL
pexelsbot-0.0.1.dist-info/top_level.txt
pexelsbot-0.0.1.dist-info/RECORD
