Metadata-Version: 2.1
Name: pexelsbot
Version: 0.0.1
Summary: pexels bot
Home-page: https://github.com/manojap/pexelsbot
Author: Manoj A.P
Author-email: manojap@outlook.com
License: UNKNOWN
Platform: UNKNOWN
Classifier: Programming Language :: Python :: 3
Classifier: License :: OSI Approved :: MIT License
Classifier: Operating System :: OS Independent
Requires-Python: >=3.6
Requires-Dist: selenium
Requires-Dist: webdriver-manager
